{
  "trade_data": {
    "SOL/USDT": {
      "asset": "SOL/USDT",
      "order_id": "ord_c88e712a44",
      "entry_price": 83.34,
      "stop_loss": 84.606429,
      "take_profit": 80.173928,
      "side": "sell",
      "quantity": 42.647837,
      "entry_time": "2026-03-31T05:37:37.425409+00:00",
      "confidence": 53,
      "tech_signal": {
        "type": "technical_signal",
        "asset": "SOL/USDT",
        "signal": "bearish",
        "confidence": 41,
        "timeframe": "1h",
        "market": "crypto",
        "rsi": 38.98,
        "macd_hist": -0.015811,
        "bb_position": 0.441,
        "volume_ratio": 0.57,
        "pattern": null,
        "entry_price": 83.34,
        "atr": 0.844286,
        "ob_imbalance": 0.0,
        "vwap_dist_pct": 0.0,
        "trend_slope": 0.02072,
        "timestamp": "2026-03-31T05:37:37.304530+00:00",
        "_ts": "2026-03-31T05:37:37.304587+00:00"
      },
      "fund_signal": {
        "type": "fundamental_signal",
        "asset": "SOL/USDT",
        "signal": "bearish",
        "sentiment_score": -59.1,
        "confidence": 59,
        "news_count": 1,
        "key_events": [
          "[Swarmode] Pr\u00e9vision 1h: -0.62% | 24h: -1.27% | R\u00e9gime: mean_reverting"
        ],
        "source": "swarmode_sim",
        "_ts": "2026-03-31T05:37:37.384411+00:00"
      },
      "regime": "sideways"
    },
    "EUR/USD": {
      "asset": "EUR/USD",
      "order_id": "ord_d8fa74dc8f",
      "entry_price": 1.1472,
      "stop_loss": 1.145625,
      "take_profit": 1.151137,
      "side": "buy",
      "quantity": 32806.764444,
      "entry_time": "2026-03-31T06:40:17.691269+00:00",
      "confidence": 48,
      "tech_signal": {
        "type": "technical_signal",
        "asset": "EUR/USD",
        "signal": "bullish",
        "confidence": 41,
        "timeframe": "1h",
        "market": "forex",
        "rsi": 61.82,
        "macd_hist": 0.000172,
        "bb_position": 0.431,
        "volume_ratio": 0.53,
        "pattern": null,
        "entry_price": 1.1472,
        "atr": 0.00105,
        "ob_imbalance": -0.1415,
        "vwap_dist_pct": 0.024,
        "trend_slope": 0.00314,
        "timestamp": "2026-03-31T06:40:12.091379+00:00",
        "_ts": "2026-03-31T06:40:12.091489+00:00"
      },
      "fund_signal": {
        "type": "fundamental_signal",
        "asset": "EUR/USD",
        "signal": "bullish",
        "sentiment_score": 74.3,
        "confidence": 74,
        "news_count": 1,
        "key_events": [
          "[Swarmode] Pr\u00e9vision 1h: +0.10% | 24h: +0.30% | R\u00e9gime: trending"
        ],
        "source": "swarmode_sim",
        "_ts": "2026-03-31T06:40:17.660076+00:00"
      },
      "regime": "sideways"
    },
    "BTC/USDT": {
      "asset": "BTC/USDT",
      "order_id": "ord_cb051c8f4d",
      "entry_price": 67367.69,
      "stop_loss": 66644.2308,
      "take_profit": 69176.338,
      "side": "buy",
      "quantity": 0.067441,
      "entry_time": "2026-03-31T08:45:32.978461+00:00",
      "confidence": 37,
      "tech_signal": {
        "type": "technical_signal",
        "asset": "BTC/USDT",
        "signal": "bullish",
        "confidence": 56,
        "timeframe": "1h",
        "market": "crypto",
        "rsi": 60.5,
        "macd_hist": 20.322905,
        "bb_position": 0.53,
        "volume_ratio": 2.17,
        "pattern": null,
        "entry_price": 67367.69,
        "atr": 475.96,
        "ob_imbalance": 0.9815,
        "vwap_dist_pct": -0.879,
        "trend_slope": -0.03583,
        "timestamp": "2026-03-31T08:45:32.793325+00:00",
        "_ts": "2026-03-31T08:45:32.793375+00:00"
      },
      "fund_signal": {
        "type": "fundamental_signal",
        "asset": "BTC/USDT",
        "sentiment_score": -2,
        "signal": "neutral",
        "confidence": 2,
        "news_count": 0,
        "key_events": [],
        "social_score": null,
        "onchain_metrics": {
          "price_usd": 66801.96,
          "volume_24h": 1221252360.6760535,
          "price_change_24h_pct": -1.42,
          "high_24h": 68408.37,
          "low_24h": 66233.13,
          "trade_count": 3663946,
          "price_change_7d_pct": null,
          "sentiment_votes_up": null,
          "sentiment_votes_down": null
        },
        "macro_events": null,
        "timestamp": "2026-03-31T08:45:23.143161+00:00",
        "_ts": "2026-03-31T08:45:23.143173+00:00"
      },
      "regime": "volatile"
    },
    "ETH/USDT": {
      "asset": "ETH/USDT",
      "order_id": "ord_b1661b0da7",
      "entry_price": 2040.1,
      "stop_loss": 2071.552299,
      "take_profit": 1961.469252,
      "side": "sell",
      "quantity": 1.526642,
      "entry_time": "2026-03-31T09:21:21.560802+00:00",
      "confidence": 57,
      "tech_signal": {
        "type": "technical_signal",
        "asset": "ETH/USDT",
        "signal": "bearish",
        "confidence": 28,
        "timeframe": "1h",
        "market": "crypto",
        "rsi": 53.17,
        "macd_hist": -1.24842,
        "bb_position": 0.349,
        "volume_ratio": 0.77,
        "pattern": null,
        "entry_price": 2040.1,
        "atr": 20.423571,
        "ob_imbalance": -0.7607,
        "vwap_dist_pct": -0.933,
        "trend_slope": -0.02654,
        "timestamp": "2026-03-31T09:21:10.515187+00:00",
        "_ts": "2026-03-31T09:21:10.515236+00:00"
      },
      "fund_signal": {
        "type": "fundamental_signal",
        "asset": "ETH/USDT",
        "signal": "bearish",
        "sentiment_score": -43.6,
        "confidence": 43,
        "news_count": 1,
        "key_events": [
          "[Swarmode] Pr\u00e9vision 1h: -0.04% | 24h: -1.47% | R\u00e9gime: mean_reverting"
        ],
        "source": "swarmode_sim",
        "_ts": "2026-03-31T09:21:21.552443+00:00"
      },
      "regime": "volatile"
    }
  },
  "positions": {
    "SOL/USDT": {
      "type": "validated_order",
      "order_id": "ord_c88e712a44",
      "asset": "SOL/USDT",
      "side": "sell",
      "order_type": "market",
      "quantity": 42.647837,
      "entry_price": 83.34,
      "stop_loss": 84.606429,
      "take_profit": 80.173928,
      "risk_reward": 2.5,
      "risk_amount_usd": 54.01,
      "risk_percent": 2.0,
      "confidence_score": 53,
      "signal_sources": [
        "ScanAgent",
        "ResearchAgent",
        "PredictAgent"
      ],
      "exchange": "binance",
      "status": "validated",
      "timestamp": "2026-03-31T05:37:37.425270+00:00"
    },
    "EUR/USD": {
      "type": "validated_order",
      "order_id": "ord_d8fa74dc8f",
      "asset": "EUR/USD",
      "side": "buy",
      "order_type": "market",
      "quantity": 32806.764444,
      "entry_price": 1.1472,
      "stop_loss": 1.145625,
      "take_profit": 1.151137,
      "risk_reward": 2.5,
      "risk_amount_usd": 51.67,
      "risk_percent": 2.0,
      "confidence_score": 48,
      "signal_sources": [
        "ScanAgent",
        "ResearchAgent",
        "PredictAgent"
      ],
      "exchange": "binance",
      "status": "validated",
      "timestamp": "2026-03-31T06:40:17.690966+00:00"
    },
    "BTC/USDT": {
      "type": "validated_order",
      "order_id": "ord_cb051c8f4d",
      "asset": "BTC/USDT",
      "side": "buy",
      "order_type": "market",
      "quantity": 0.067441,
      "entry_price": 67367.69,
      "stop_loss": 66644.2308,
      "take_profit": 69176.338,
      "risk_reward": 2.5,
      "risk_amount_usd": 48.79,
      "risk_percent": 2.0,
      "confidence_score": 37,
      "signal_sources": [
        "ScanAgent",
        "ResearchAgent",
        "PredictAgent"
      ],
      "exchange": "binance",
      "status": "validated",
      "timestamp": "2026-03-31T08:45:32.978371+00:00"
    },
    "ETH/USDT": {
      "type": "validated_order",
      "order_id": "ord_b1661b0da7",
      "asset": "ETH/USDT",
      "side": "sell",
      "order_type": "market",
      "quantity": 1.526642,
      "entry_price": 2040.1,
      "stop_loss": 2071.552299,
      "take_profit": 1961.469252,
      "risk_reward": 2.5,
      "risk_amount_usd": 48.02,
      "risk_percent": 2.0,
      "confidence_score": 57,
      "signal_sources": [
        "ScanAgent",
        "ResearchAgent",
        "PredictAgent"
      ],
      "exchange": "binance",
      "status": "validated",
      "timestamp": "2026-03-31T09:21:21.560719+00:00"
    }
  }
}